js_lib_leaflet/__init__.py
js_lib_leaflet/apps.py
js_lib_leaflet/static/js_lib_leaflet/leaflet-src.esm.js
js_lib_leaflet/static/js_lib_leaflet/leaflet-src.esm.js.map
js_lib_leaflet/static/js_lib_leaflet/leaflet-src.js
js_lib_leaflet/static/js_lib_leaflet/leaflet-src.js.map
js_lib_leaflet/static/js_lib_leaflet/leaflet.css
js_lib_leaflet/static/js_lib_leaflet/leaflet.js
js_lib_leaflet/static/js_lib_leaflet/leaflet.js.map
js_lib_leaflet/static/js_lib_leaflet/images/layers-2x.png
js_lib_leaflet/static/js_lib_leaflet/images/layers.png
js_lib_leaflet/static/js_lib_leaflet/images/marker-icon-2x.png
js_lib_leaflet/static/js_lib_leaflet/images/marker-icon.png
js_lib_leaflet/static/js_lib_leaflet/images/marker-shadow.png
django_js_lib_leaflet-1.9.4.1.dist-info/LICENSE
django_js_lib_leaflet-1.9.4.1.dist-info/WHEEL
django_js_lib_leaflet-1.9.4.1.dist-info/METADATA
django_js_lib_leaflet-1.9.4.1.dist-info/RECORD
