Metadata-Version: 2.1
Name: django-js-lib-leaflet
Version: 1.9.4.1
Summary: Leaflet Repackaged for Django
Classifier: License :: OSI Approved :: BSD License
